django_simpleauth-0.3.dist-info/DESCRIPTION.rst
django_simpleauth-0.3.dist-info/METADATA
django_simpleauth-0.3.dist-info/RECORD
django_simpleauth-0.3.dist-info/WHEEL
django_simpleauth-0.3.dist-info/metadata.json
django_simpleauth-0.3.dist-info/top_level.txt
simpleauth/__init__.py
simpleauth/admin.py
simpleauth/apps.py
simpleauth/forms.py
simpleauth/models.py
simpleauth/tests.py
simpleauth/urls.py
simpleauth/views.py
simpleauth/migrations/0001_initial.py
simpleauth/migrations/__init__.py
simpleauth/templates/simpleauth/fourohfour.html
simpleauth/templates/simpleauth/index.html
simpleauth/templates/simpleauth/inside.html
simpleauth/templates/simpleauth/outside.html
simpleauth/templates/simpleauth/register.html
simpleauth/templates/simpleauth/thanks.html
